{
  "bindings": [
    {
      "code": "ArrowLeft",
      "control": false,
      "command": "navigate-cursor-left"
    },
    {
      "code": "KeyB",
      "control": true,
      "command": "navigate-cursor-left"
    },

    {
      "code": "ArrowRight",
      "control": false,
      "command": "navigate-cursor-right"
    },
    {
      "code": "KeyF",
      "control": true,
      "command": "navigate-cursor-right"
    },


    {
      "code": "ArrowUp",
      "control": false,
      "command": "navigate-cursor-up"
    },
    {
      "code": "KeyP",
      "control": true,
      "command": "navigate-cursor-up"
    },
    {
      "code": "ArrowDown",
      "control": false,
      "command": "navigate-cursor-down"
    },
    {
      "code": "KeyN",
      "control": true,
      "command": "navigate-cursor-down"
    }
  ]
}
